graylogger/__init__.py
graylogger/_version.py
graylogger/graylogger.py
logproducer/__init__.py
logproducer/logproducer.py
tangods_graylogger-1.0.0.dist-info/LICENSE
tangods_graylogger-1.0.0.dist-info/METADATA
tangods_graylogger-1.0.0.dist-info/WHEEL
tangods_graylogger-1.0.0.dist-info/entry_points.txt
tangods_graylogger-1.0.0.dist-info/top_level.txt
tangods_graylogger-1.0.0.dist-info/RECORD
