Metadata-Version: 2.2
Name: tangods-graylogger
Version: 1.0.0
Summary: A tango device server to catch logs on the old log4tango API and send them to Graylogger using GELF and HTTP.
Author-email: Antonio Bartalesi <antonio.bartalesi@gmail.com>
Project-URL: repository, https://gitlab.com/ABartalesi/graylogger-tangods
Classifier: License :: OSI Approved :: GNU General Public License v3 or later (GPLv3+)
License-File: LICENSE
Requires-Dist: pytango
Requires-Dist: requests
Provides-Extra: test
Requires-Dist: pytest; extra == "test"
